django_giom-0.1.1.dist-info/metadata.json
django_giom-0.1.1.dist-info/DESCRIPTION.rst
django_giom-0.1.1.dist-info/METADATA
django_giom-0.1.1.dist-info/RECORD
django_giom-0.1.1.dist-info/top_level.txt
django_giom-0.1.1.dist-info/WHEEL
giom_data/api.py
giom_data/GiomDataReader.py
giom_data/__init__.py
giom_data/urls.py
giom_data/view.py
giom_data/tasks.py
giom_data/management/__init__.py
giom_data/management/commands/read_giom_csv.py
giom_data/management/commands/__init__.py
giom_data/management/commands/read_giom_xml.py
giom_data/management/commands/refresh_giom_data.py
giom_data/templates/__init__.py
giom_data/templates/giom_data.html
